ducle_package/__init__.py
ducle_package/module.py
ducle_package-0.0.1.dist-info/METADATA
ducle_package-0.0.1.dist-info/WHEEL
ducle_package-0.0.1.dist-info/top_level.txt
ducle_package-0.0.1.dist-info/RECORD
