Metadata-Version: 2.1
Name: ducle_package
Version: 0.0.1
Summary: package description
Author-email: Example Author <author@example.com>
Requires-Python: >=3.7
Requires-Dist: requests >2.26.0
Requires-Dist: pandas
